CHANGES.txt
COPYRIGHT.txt
LICENSE.txt
MANIFEST.in
README.txt
bootstrap.py
buildout.cfg
setup.py
tox.ini
src/zope/__init__.py
src/zope.renderer.egg-info/PKG-INFO
src/zope.renderer.egg-info/SOURCES.txt
src/zope.renderer.egg-info/dependency_links.txt
src/zope.renderer.egg-info/namespace_packages.txt
src/zope.renderer.egg-info/not-zip-safe
src/zope.renderer.egg-info/requires.txt
src/zope.renderer.egg-info/top_level.txt
src/zope/renderer/__init__.py
src/zope/renderer/_compat.py
src/zope/renderer/configure.zcml
src/zope/renderer/i18n.py
src/zope/renderer/interfaces.py
src/zope/renderer/plaintext.py
src/zope/renderer/rest.py
src/zope/renderer/stx.py
src/zope/renderer/tests.py
src/zope/renderer/vocabulary.py